<?xml version="1.0" encoding="UTF-8" standalone="no"?>
<layoutVars>
<variable key="5139">-2146664148</variable>
<variable key="5140">2048</variable>
<variable key="4120">620756991</variable>
<variable key="5154">2049</variable>
<variable key="2852">319951120</variable>
<variable key="2853">387323156</variable>
<variable key="2854">454695192</variable>
<variable key="4646">-2129022736</variable>
<variable key="2855">572588031</variable>
<variable key="4647">16777216</variable>
<variable key="2856">319951120</variable>
<variable key="5160">1597615</variable>
<variable key="2857">-236</variable>
<variable key="5161">16777215</variable>
<variable key="2858">-42497</variable>
<variable key="2859">-268435456</variable>
<variable key="2860">1023</variable>
<variable key="2862">-1</variable>
<variable key="2863">691470335</variable>
<variable key="2864">642008373</variable>
<variable key="2865">-13162457</variable>
<variable key="2866">-1</variable>
<variable key="2867">589579832</variable>
<variable key="2868">842019105</variable>
<variable key="2869">33646952</variable>
<variable key="4154">360798</variable>
<variable key="4155">10186752</variable>
<variable key="4939">-2146135748</variable>
<variable key="4684">-2147360683</variable>
<variable key="4685">3600383</variable>
<variable key="4954">-2147327930</variable>
<variable key="4955">4100095</variable>
<variable key="2912">32</variable>
<variable key="2913">-2130706433</variable>
<variable key="4705">-2147237488</variable>
<variable key="2914">8390656</variable>
<variable key="4706">2048</variable>
<variable key="2915">-2130509472</variable>
<variable key="2916">33554431</variable>
<variable key="2917">-2146664273</variable>
<variable key="2918">4095</variable>
<variable key="2919">-2130394560</variable>
<variable key="2920">28491776</variable>
<variable key="2921">-2146520512</variable>
<variable key="2922">369094656</variable>
<variable key="2923">1597615</variable>
<variable key="2924">16777215</variable>
<variable key="2925">-2144451968</variable>
<variable key="2926">2048</variable>
<variable key="2927">811584</variable>
<variable key="2929">318767104</variable>
<variable key="2930">369098752</variable>
<variable key="2931">352321536</variable>
<variable key="4723">1597615</variable>
<variable key="2932">385875968</variable>
<variable key="4724">16777215</variable>
<variable key="2933">1597615</variable>
<variable key="2934">16777215</variable>
<variable key="2935">-2146885110</variable>
<variable key="2936">15155700</variable>
<variable key="2937">-2146041344</variable>
<variable key="2938">8390656</variable>
<variable key="2939">1597615</variable>
<variable key="2940">16777215</variable>
<variable key="2941">1597615</variable>
<variable key="2942">16777215</variable>
<variable key="2943">-2147196643</variable>
<variable key="2944">8372224</variable>
<variable key="2945">1597615</variable>
<variable key="2946">16777215</variable>
<variable key="2947">1597615</variable>
<variable key="2948">16777215</variable>
<variable key="2949">1597615</variable>
<variable key="4997">-1</variable>
<variable key="2950">16777215</variable>
<variable key="4998">-1</variable>
<variable key="2951">1597615</variable>
<variable key="4999">-1</variable>
<variable key="2952">16777215</variable>
<variable key="5000">-1</variable>
<variable key="2953">1597615</variable>
<variable key="3465">127</variable>
<variable key="3721">100992003</variable>
<variable key="5001">-1</variable>
<variable key="2954">16777215</variable>
<variable key="3722">-13304057</variable>
<variable key="5002">-1</variable>
<variable key="2955">1102022</variable>
<variable key="3723">4198400</variable>
<variable key="5003">-1</variable>
<variable key="2956">16777215</variable>
<variable key="5004">-1</variable>
<variable key="2957">436207616</variable>
<variable key="5005">-1</variable>
<variable key="5006">-1</variable>
<variable key="2959">1597615</variable>
<variable key="5007">-1</variable>
<variable key="2960">16777215</variable>
<variable key="5008">-1</variable>
<variable key="2961">1597615</variable>
<variable key="5009">-1</variable>
<variable key="2962">16777215</variable>
<variable key="5010">-1</variable>
<variable key="2963">369098752</variable>
<variable key="2964">402653184</variable>
<variable key="2965">1597615</variable>
<variable key="2966">16777215</variable>
<variable key="5014">-2112794544</variable>
<variable key="2967">1597615</variable>
<variable key="5015">33554432</variable>
<variable key="2968">16777215</variable>
<variable key="5016">-2112794544</variable>
<variable key="2969">1597615</variable>
<variable key="5017">33554832</variable>
<variable key="2970">16777215</variable>
<variable key="5018">-2112794544</variable>
<variable key="2971">1597615</variable>
<variable key="5019">45694975</variable>
<variable key="2972">16777215</variable>
<variable key="4764">-2146090718</variable>
<variable key="5020">-2112794544</variable>
<variable key="2973">-2147098374</variable>
<variable key="4765">8392703</variable>
<variable key="5021">45694462</variable>
<variable key="2974">10187906</variable>
<variable key="4254">-2147352464</variable>
<variable key="4510">-51969</variable>
<variable key="2975">-2147348352</variable>
<variable key="4255">1075</variable>
<variable key="4511">402653184</variable>
<variable key="2976">5607423</variable>
<variable key="4512">167772160</variable>
<variable key="2977">-2146115221</variable>
<variable key="4513">-2146827988</variable>
<variable key="2978">2048</variable>
<variable key="4514">8390656</variable>
<variable key="2979">-2146664148</variable>
<variable key="4515">1597615</variable>
<variable key="2980">4196352</variable>
<variable key="4516">16777215</variable>
<variable key="2981">-2146303776</variable>
<variable key="2982">8392703</variable>
<variable key="2983">-2147348360</variable>
<variable key="2984">3073</variable>
<variable key="2985">1597615</variable>
<variable key="2986">16777215</variable>
<variable key="2987">-2147176268</variable>
<variable key="2988">1805193</variable>
<variable key="2989">-2147344282</variable>
<variable key="2990">4194304</variable>
<variable key="2991">-2145025360</variable>
<variable key="2992">8390656</variable>
<variable key="2993">-2146848419</variable>
<variable key="2994">4196352</variable>
<variable key="2995">2360096</variable>
<variable key="2996">8374271</variable>
<variable key="3769">385875968</variable>
<variable key="3770">436207616</variable>
<variable key="4794">-1</variable>
<variable key="5050">-2112794544</variable>
<variable key="5051">33554432</variable>
<variable key="5052">-2112794544</variable>
<variable key="5053">33554832</variable>
<variable key="4798">-2146377458</variable>
<variable key="5054">-2112794544</variable>
<variable key="5055">45694975</variable>
<variable key="5056">-2112794544</variable>
<variable key="5057">45694462</variable>
<variable key="5058">-2112794544</variable>
<variable key="5059">33554432</variable>
<variable key="5060">-2112794544</variable>
<variable key="5061">33554832</variable>
<variable key="5062">-2112794544</variable>
<variable key="5063">45694975</variable>
<variable key="5064">-2112794544</variable>
<variable key="5065">45694462</variable>
<variable key="4813">-2146897680</variable>
<variable key="4814">1805193</variable>
<variable key="5079">65535</variable>
<variable key="5081">1597615</variable>
<variable key="5082">16777215</variable>
<variable key="4322">1597615</variable>
<variable key="4323">16777215</variable>
<variable key="4324">1597615</variable>
<variable key="4325">16777215</variable>
<variable key="3825">-2146827988</variable>
</layoutVars>
